{
  "generatedAt": "2026-06-12T16:54:47+00:00",
  "lastCrawl": "2026-06-13",
  "crawl": {
    "servers": 11574,
    "tools": 143236,
    "snapshots": 1879554,
    "stealthTools": 7708,
    "crossRegistryAnomalies": 28066,
    "crossSourceAnomalies": 51150
  },
  "registries": [
    {
      "name": "Official",
      "servers": 5300,
      "color": "#6366f1"
    },
    {
      "name": "Glama",
      "servers": 4645,
      "color": "#8b5cf6"
    },
    {
      "name": "Smithery",
      "servers": 1629,
      "color": "#06b6d4"
    }
  ],
  "health": [
    {
      "name": "Healthy",
      "value": 2561,
      "color": "#22c55e"
    },
    {
      "name": "Unhealthy",
      "value": 2083,
      "color": "#ef4444"
    },
    {
      "name": "Unknown",
      "value": 6930,
      "color": "#6b7280"
    }
  ],
  "tdqs": [
    {
      "grade": "A",
      "count": 2289,
      "color": "#22c55e"
    },
    {
      "grade": "B",
      "count": 470,
      "color": "#84cc16"
    },
    {
      "grade": "C",
      "count": 133,
      "color": "#f59e0b"
    },
    {
      "grade": "D",
      "count": 5,
      "color": "#ef4444"
    },
    {
      "grade": "미평가",
      "count": 8677,
      "color": "#374151"
    }
  ],
  "protocol": [
    {
      "name": "2024-11-05",
      "value": 4274,
      "color": "#6366f1"
    },
    {
      "name": "2025-03-26",
      "value": 1969,
      "color": "#06b6d4"
    },
    {
      "name": "2025-06-18",
      "value": 315,
      "color": "#8b5cf6"
    },
    {
      "name": "2025-11-05",
      "value": 6,
      "color": "#a78bfa"
    },
    {
      "name": "2025-11-25",
      "value": 87,
      "color": "#f59e0b"
    },
    {
      "name": "미보고",
      "value": 4923,
      "color": "#374151"
    }
  ],
  "toolDist": [
    {
      "name": "0",
      "servers": 4285,
      "color": "#6b7280"
    },
    {
      "name": "1-5",
      "servers": 2285,
      "color": "#06b6d4"
    },
    {
      "name": "6-10",
      "servers": 1416,
      "color": "#6366f1"
    },
    {
      "name": "11-20",
      "servers": 958,
      "color": "#8b5cf6"
    },
    {
      "name": "20+",
      "servers": 2630,
      "color": "#22c55e"
    }
  ],
  "topByUse": [
    {
      "name": "EthanHenrickson/math-mcp",
      "value": 619577,
      "registry": "smithery"
    },
    {
      "name": "henry-ships/sparkforge",
      "value": 60249,
      "registry": "smithery"
    },
    {
      "name": "googlesheets",
      "value": 47742,
      "registry": "smithery"
    },
    {
      "name": "gmail",
      "value": 37423,
      "registry": "smithery"
    },
    {
      "name": "exa",
      "value": 27835,
      "registry": "smithery"
    },
    {
      "name": "clay-inc/clay-mcp",
      "value": 21031,
      "registry": "smithery"
    },
    {
      "name": "openclaw-hal9000/romulus-31780",
      "value": 18448,
      "registry": "smithery"
    },
    {
      "name": "creativelead/unclick",
      "value": 16571,
      "registry": "smithery"
    },
    {
      "name": "king-of-the-grackles/discourse-forum-mcp",
      "value": 16046,
      "registry": "smithery"
    },
    {
      "name": "hamid-vakilzadeh/mcpsemanticscholar",
      "value": 15795,
      "registry": "smithery"
    }
  ],
  "topByTools": [
    {
      "name": "pipeworx gateway",
      "value": 2552,
      "registry": "smithery"
    },
    {
      "name": "AdButler",
      "value": 622,
      "registry": "official"
    },
    {
      "name": "APIbase",
      "value": 618,
      "registry": "smithery"
    },
    {
      "name": "UnClick",
      "value": 451,
      "registry": "smithery"
    },
    {
      "name": "TheProtocol — Sovereign AI Agent Platform",
      "value": 380,
      "registry": "official"
    },
    {
      "name": "Tenzro Ledger MCP",
      "value": 379,
      "registry": "official"
    },
    {
      "name": "Tenzro Ledger MCP",
      "value": 379,
      "registry": "glama"
    },
    {
      "name": "PostHog",
      "value": 329,
      "registry": "smithery"
    },
    {
      "name": "Crawlora",
      "value": 319,
      "registry": "smithery"
    },
    {
      "name": "official::io.github.getgapup/mcp-knowledge",
      "value": 271,
      "registry": "official"
    }
  ],
  "stealthByServer": [
    {
      "name": "smithery::blackboxfoundry/livedatalink",
      "value": 1014,
      "registry": "smithery"
    },
    {
      "name": "smithery::delx/witness-protocol",
      "value": 534,
      "registry": "smithery"
    },
    {
      "name": "glama::io.github.ABTdomain/domainkits-mcp",
      "value": 494,
      "registry": "glama"
    },
    {
      "name": "smithery::netfluid/NFLD",
      "value": 268,
      "registry": "smithery"
    },
    {
      "name": "smithery::vicente-litvak/siimaster",
      "value": 188,
      "registry": "smithery"
    },
    {
      "name": "smithery::Plagtech/Spraay-x402-mcp",
      "value": 174,
      "registry": "smithery"
    },
    {
      "name": "smithery::rafaelkocurek-nvob/agentview",
      "value": 156,
      "registry": "smithery"
    },
    {
      "name": "smithery::marcio-5hzu/contazz-autopilot",
      "value": 147,
      "registry": "smithery"
    },
    {
      "name": "glama::network.tenzro/tenzro",
      "value": 121,
      "registry": "glama"
    },
    {
      "name": "smithery::vortxai/emem",
      "value": 120,
      "registry": "smithery"
    }
  ],
  "stealthByRegistry": [
    {
      "name": "smithery",
      "value": 939
    },
    {
      "name": "glama",
      "value": 157
    }
  ],
  "crossRegistrySamples": [
    {
      "server": "official::io.github.0nork/0nMCP",
      "registryA": "official::io.github.0nork/0nMCP",
      "registryB": "glama::io.github.0nork/0nMCP",
      "match": "remote_url"
    },
    {
      "server": "official::io.github.davidsiegel59/4bots-content",
      "registryA": "official::io.github.davidsiegel59/4bots-content",
      "registryB": "glama::io.github.davidsiegel59/4bots-content",
      "match": "remote_url"
    },
    {
      "server": "official::net.4bots/4bots",
      "registryA": "official::net.4bots/4bots",
      "registryB": "glama::net.4bots/4bots",
      "match": "remote_url"
    },
    {
      "server": "official::io.github.andrew-ji-cupix/cupix-compass",
      "registryA": "official::io.github.andrew-ji-cupix/cupix-compass",
      "registryB": "glama::io.github.andrew-ji-cupix/cupix-compass",
      "match": "remote_url"
    },
    {
      "server": "official::io.github.khalidsaidi/a2abench",
      "registryA": "official::io.github.khalidsaidi/a2abench",
      "registryB": "glama::io.github.khalidsaidi/a2abench",
      "match": "remote_url"
    },
    {
      "server": "official::io.github.atomadictech/aaaa-nexus",
      "registryA": "official::io.github.atomadictech/aaaa-nexus",
      "registryB": "glama::io.github.atomadictech/aaaa-nexus",
      "match": "remote_url"
    },
    {
      "server": "official::io.scanbimlabs/acc-mcp",
      "registryA": "official::io.scanbimlabs/acc-mcp",
      "registryB": "glama::io.scanbimlabs/acc-mcp",
      "match": "remote_url"
    },
    {
      "server": "official::dev.cz-agents/adis",
      "registryA": "official::dev.cz-agents/adis",
      "registryB": "glama::dev.cz-agents/adis",
      "match": "remote_url"
    }
  ],
  "crossSourceSamples": [
    {
      "tool": "get_template",
      "server": "glama::net.4bots/4bots",
      "sourceA": "registry",
      "sourceB": "direct_mcp"
    },
    {
      "tool": "list_products",
      "server": "glama::ai.agenticshelf/mcp",
      "sourceA": "registry",
      "sourceB": "direct_mcp"
    },
    {
      "tool": "list_numbers",
      "server": "glama::dev.agentsim/mcp",
      "sourceA": "registry",
      "sourceB": "direct_mcp"
    },
    {
      "tool": "provision_number",
      "server": "glama::dev.agentsim/mcp",
      "sourceA": "registry",
      "sourceB": "direct_mcp"
    },
    {
      "tool": "register",
      "server": "glama::io.github.JoursBleu/agent-tools-mcp",
      "sourceA": "registry",
      "sourceB": "direct_mcp"
    },
    {
      "tool": "search",
      "server": "glama::io.github.JoursBleu/agent-tools-mcp",
      "sourceA": "registry",
      "sourceB": "direct_mcp"
    },
    {
      "tool": "analyze_business_context",
      "server": "glama::io.github.tenkai2018/ai-business-system-advisor-mcp",
      "sourceA": "registry",
      "sourceB": "direct_mcp"
    },
    {
      "tool": "assess_trust_control_risks",
      "server": "glama::io.github.tenkai2018/ai-business-system-advisor-mcp",
      "sourceA": "registry",
      "sourceB": "direct_mcp"
    }
  ],
  "stealthSamples": [
    {
      "tool": "mcp-security-scanner",
      "server": "glama::io.github.0xAxiom/axiom-agentic-tools"
    },
    {
      "tool": "archive_report_brief",
      "server": "glama::io.github.DigbyO/colour-memory"
    },
    {
      "tool": "heritage_evolution_palette",
      "server": "glama::io.github.DigbyO/colour-memory"
    },
    {
      "tool": "brand_collision_check",
      "server": "glama::io.github.DigbyO/colour-memory"
    },
    {
      "tool": "product_line_colour_namer",
      "server": "glama::io.github.DigbyO/colour-memory"
    },
    {
      "tool": "ui_state_palette",
      "server": "glama::io.github.DigbyO/colour-memory"
    },
    {
      "tool": "active",
      "server": "glama::io.github.ABTdomain/domainkits-mcp"
    },
    {
      "tool": "aged",
      "server": "glama::io.github.ABTdomain/domainkits-mcp"
    }
  ],
  "trend": [
    {
      "date": "2026-06-01",
      "serversCumulative": 9378,
      "newServers": 9378,
      "snapshots": 119869,
      "snapshotsCumulative": 119869,
      "tools": 90976,
      "toolsCumulative": 90976,
      "changes": 0,
      "stealth": 80,
      "crossRegistry": 1912,
      "crossSource": 1125,
      "tdqsAvg": 0
    },
    {
      "date": "2026-06-02",
      "serversCumulative": 9459,
      "newServers": 81,
      "snapshots": 121086,
      "snapshotsCumulative": 240955,
      "tools": 92304,
      "toolsCumulative": 93023,
      "changes": 1687,
      "stealth": 179,
      "crossRegistry": 1910,
      "crossSource": 1670,
      "tdqsAvg": 0
    },
    {
      "date": "2026-06-03",
      "serversCumulative": 9541,
      "newServers": 82,
      "snapshots": 122054,
      "snapshotsCumulative": 363009,
      "tools": 92906,
      "toolsCumulative": 93741,
      "changes": 2408,
      "stealth": 38,
      "crossRegistry": 1934,
      "crossSource": 1113,
      "tdqsAvg": 0
    },
    {
      "date": "2026-06-04",
      "serversCumulative": 9830,
      "newServers": 289,
      "snapshots": 126160,
      "snapshotsCumulative": 489169,
      "tools": 96844,
      "toolsCumulative": 98240,
      "changes": 11687,
      "stealth": 41,
      "crossRegistry": 2069,
      "crossSource": 1577,
      "tdqsAvg": 0
    },
    {
      "date": "2026-06-05",
      "serversCumulative": 10033,
      "newServers": 203,
      "snapshots": 133471,
      "snapshotsCumulative": 622640,
      "tools": 100773,
      "toolsCumulative": 103036,
      "changes": 9689,
      "stealth": 49,
      "crossRegistry": 2120,
      "crossSource": 5050,
      "tdqsAvg": 0
    },
    {
      "date": "2026-06-06",
      "serversCumulative": 10103,
      "newServers": 70,
      "snapshots": 134332,
      "snapshotsCumulative": 756972,
      "tools": 101308,
      "toolsCumulative": 104088,
      "changes": 7284,
      "stealth": 41,
      "crossRegistry": 2125,
      "crossSource": 1088,
      "tdqsAvg": 0
    },
    {
      "date": "2026-06-07",
      "serversCumulative": 10163,
      "newServers": 60,
      "snapshots": 135279,
      "snapshotsCumulative": 892251,
      "tools": 102279,
      "toolsCumulative": 105291,
      "changes": 2982,
      "stealth": 145,
      "crossRegistry": 2116,
      "crossSource": 1249,
      "tdqsAvg": 0
    },
    {
      "date": "2026-06-08",
      "serversCumulative": 10230,
      "newServers": 67,
      "snapshots": 142081,
      "snapshotsCumulative": 1034332,
      "tools": 104877,
      "toolsCumulative": 107435,
      "changes": 6119,
      "stealth": 1123,
      "crossRegistry": 2132,
      "crossSource": 6364,
      "tdqsAvg": 0
    },
    {
      "date": "2026-06-09",
      "serversCumulative": 10472,
      "newServers": 242,
      "snapshots": 148641,
      "snapshotsCumulative": 1182973,
      "tools": 107485,
      "toolsCumulative": 111146,
      "changes": 4277,
      "stealth": 1294,
      "crossRegistry": 2198,
      "crossSource": 6502,
      "tdqsAvg": 0
    },
    {
      "date": "2026-06-10",
      "serversCumulative": 10548,
      "newServers": 76,
      "snapshots": 146194,
      "snapshotsCumulative": 1329167,
      "tools": 108321,
      "toolsCumulative": 112576,
      "changes": 7171,
      "stealth": 558,
      "crossRegistry": 2213,
      "crossSource": 4324,
      "tdqsAvg": 0
    },
    {
      "date": "2026-06-11",
      "serversCumulative": 10913,
      "newServers": 365,
      "snapshots": 174294,
      "snapshotsCumulative": 1503461,
      "tools": 124404,
      "toolsCumulative": 128371,
      "changes": 4993,
      "stealth": 1734,
      "crossRegistry": 2340,
      "crossSource": 9162,
      "tdqsAvg": 0
    },
    {
      "date": "2026-06-12",
      "serversCumulative": 11233,
      "newServers": 320,
      "snapshots": 185945,
      "snapshotsCumulative": 1689406,
      "tools": 133018,
      "toolsCumulative": 138365,
      "changes": 16654,
      "stealth": 1330,
      "crossRegistry": 2435,
      "crossSource": 6771,
      "tdqsAvg": 0
    },
    {
      "date": "2026-06-13",
      "serversCumulative": 11574,
      "newServers": 341,
      "snapshots": 190148,
      "snapshotsCumulative": 1879554,
      "tools": 137275,
      "toolsCumulative": 143236,
      "changes": 12459,
      "stealth": 1096,
      "crossRegistry": 2562,
      "crossSource": 5155,
      "tdqsAvg": 0
    }
  ],
  "registryTrend": [
    {
      "date": "2026-06-01",
      "official_servers": 4329,
      "official_new": 4329,
      "official_tools": 32675,
      "official_changes": 0,
      "glama_servers": 3696,
      "glama_new": 3696,
      "glama_tools": 33252,
      "glama_changes": 0,
      "smithery_servers": 1353,
      "smithery_new": 1353,
      "smithery_tools": 25049,
      "smithery_changes": 0
    },
    {
      "date": "2026-06-02",
      "official_servers": 4387,
      "official_new": 58,
      "official_tools": 33454,
      "official_changes": 860,
      "glama_servers": 3696,
      "glama_new": 0,
      "glama_tools": 33361,
      "glama_changes": 761,
      "smithery_servers": 1376,
      "smithery_new": 23,
      "smithery_tools": 25489,
      "smithery_changes": 66
    },
    {
      "date": "2026-06-03",
      "official_servers": 4428,
      "official_new": 41,
      "official_tools": 33909,
      "official_changes": 868,
      "glama_servers": 3727,
      "glama_new": 31,
      "glama_tools": 33461,
      "glama_changes": 1511,
      "smithery_servers": 1386,
      "smithery_new": 10,
      "smithery_tools": 25536,
      "smithery_changes": 29
    },
    {
      "date": "2026-06-04",
      "official_servers": 4514,
      "official_new": 86,
      "official_tools": 35164,
      "official_changes": 3884,
      "glama_servers": 3889,
      "glama_new": 162,
      "glama_tools": 35305,
      "glama_changes": 7721,
      "smithery_servers": 1427,
      "smithery_new": 41,
      "smithery_tools": 26375,
      "smithery_changes": 82
    },
    {
      "date": "2026-06-05",
      "official_servers": 4586,
      "official_new": 72,
      "official_tools": 37064,
      "official_changes": 4085,
      "glama_servers": 3955,
      "glama_new": 66,
      "glama_tools": 37054,
      "glama_changes": 5581,
      "smithery_servers": 1492,
      "smithery_new": 65,
      "smithery_tools": 26655,
      "smithery_changes": 23
    },
    {
      "date": "2026-06-06",
      "official_servers": 4617,
      "official_new": 31,
      "official_tools": 37230,
      "official_changes": 1101,
      "glama_servers": 3983,
      "glama_new": 28,
      "glama_tools": 37390,
      "glama_changes": 6139,
      "smithery_servers": 1503,
      "smithery_new": 11,
      "smithery_tools": 26688,
      "smithery_changes": 44
    },
    {
      "date": "2026-06-07",
      "official_servers": 4645,
      "official_new": 28,
      "official_tools": 37573,
      "official_changes": 834,
      "glama_servers": 3993,
      "glama_new": 10,
      "glama_tools": 37661,
      "glama_changes": 2125,
      "smithery_servers": 1525,
      "smithery_new": 22,
      "smithery_tools": 27045,
      "smithery_changes": 23
    },
    {
      "date": "2026-06-08",
      "official_servers": 4699,
      "official_new": 54,
      "official_tools": 38271,
      "official_changes": 2663,
      "glama_servers": 3993,
      "glama_new": 0,
      "glama_tools": 37994,
      "glama_changes": 3352,
      "smithery_servers": 1538,
      "smithery_new": 13,
      "smithery_tools": 28612,
      "smithery_changes": 104
    },
    {
      "date": "2026-06-09",
      "official_servers": 4780,
      "official_new": 81,
      "official_tools": 38904,
      "official_changes": 415,
      "glama_servers": 4143,
      "glama_new": 150,
      "glama_tools": 39561,
      "glama_changes": 2657,
      "smithery_servers": 1549,
      "smithery_new": 11,
      "smithery_tools": 29020,
      "smithery_changes": 1205
    },
    {
      "date": "2026-06-10",
      "official_servers": 4847,
      "official_new": 67,
      "official_tools": 40148,
      "official_changes": 1723,
      "glama_servers": 4147,
      "glama_new": 4,
      "glama_tools": 39813,
      "glama_changes": 4192,
      "smithery_servers": 1554,
      "smithery_new": 5,
      "smithery_tools": 28360,
      "smithery_changes": 1256
    },
    {
      "date": "2026-06-11",
      "official_servers": 4986,
      "official_new": 139,
      "official_tools": 46861,
      "official_changes": 966,
      "glama_servers": 4347,
      "glama_new": 200,
      "glama_tools": 47525,
      "glama_changes": 2558,
      "smithery_servers": 1580,
      "smithery_new": 26,
      "smithery_tools": 30018,
      "smithery_changes": 1469
    },
    {
      "date": "2026-06-12",
      "official_servers": 5133,
      "official_new": 147,
      "official_tools": 51055,
      "official_changes": 4268,
      "glama_servers": 4488,
      "glama_new": 141,
      "glama_tools": 52016,
      "glama_changes": 9120,
      "smithery_servers": 1612,
      "smithery_new": 32,
      "smithery_tools": 29947,
      "smithery_changes": 3266
    },
    {
      "date": "2026-06-13",
      "official_servers": 5300,
      "official_new": 167,
      "official_tools": 53358,
      "official_changes": 3069,
      "glama_servers": 4645,
      "glama_new": 157,
      "glama_tools": 54125,
      "glama_changes": 6614,
      "smithery_servers": 1629,
      "smithery_new": 17,
      "smithery_tools": 29792,
      "smithery_changes": 2776
    }
  ],
  "cumulativeCollectors": [
    {
      "name": "official",
      "servers": 5300,
      "tools": 55167,
      "changeBreakdown": {
        "description_modified": 0,
        "schema_modified": 0,
        "both_modified": 0,
        "removed": 0
      },
      "color": "#6366f1"
    },
    {
      "name": "glama",
      "servers": 4645,
      "tools": 55505,
      "changeBreakdown": {
        "description_modified": 15771,
        "schema_modified": 2812,
        "both_modified": 1697,
        "removed": 7798
      },
      "color": "#8b5cf6"
    },
    {
      "name": "smithery",
      "servers": 1629,
      "tools": 32564,
      "changeBreakdown": {
        "description_modified": 120,
        "schema_modified": 107,
        "both_modified": 79,
        "removed": 289
      },
      "color": "#06b6d4"
    },
    {
      "name": "direct_mcp",
      "servers": 6431,
      "tools": 122647,
      "changeBreakdown": {
        "description_modified": 35287,
        "schema_modified": 5931,
        "both_modified": 3957,
        "removed": 13562
      },
      "color": "#10b981"
    }
  ],
  "changeTimeline": [
    {
      "date": "2026-06-02",
      "description_modified": 1167,
      "schema_modified": 118,
      "both_modified": 62,
      "removed": 340
    },
    {
      "date": "2026-06-03",
      "description_modified": 1772,
      "schema_modified": 202,
      "both_modified": 118,
      "removed": 316
    },
    {
      "date": "2026-06-04",
      "description_modified": 7154,
      "schema_modified": 1921,
      "both_modified": 1937,
      "removed": 675
    },
    {
      "date": "2026-06-05",
      "description_modified": 8248,
      "schema_modified": 470,
      "both_modified": 187,
      "removed": 784
    },
    {
      "date": "2026-06-06",
      "description_modified": 5766,
      "schema_modified": 354,
      "both_modified": 187,
      "removed": 977
    },
    {
      "date": "2026-06-07",
      "description_modified": 1966,
      "schema_modified": 85,
      "both_modified": 87,
      "removed": 844
    },
    {
      "date": "2026-06-08",
      "description_modified": 2918,
      "schema_modified": 272,
      "both_modified": 1720,
      "removed": 1209
    },
    {
      "date": "2026-06-09",
      "description_modified": 791,
      "schema_modified": 233,
      "both_modified": 824,
      "removed": 2429
    },
    {
      "date": "2026-06-10",
      "description_modified": 2306,
      "schema_modified": 2332,
      "both_modified": 156,
      "removed": 2377
    },
    {
      "date": "2026-06-11",
      "description_modified": 2299,
      "schema_modified": 150,
      "both_modified": 111,
      "removed": 2433
    },
    {
      "date": "2026-06-12",
      "description_modified": 9396,
      "schema_modified": 2467,
      "both_modified": 139,
      "removed": 4652
    },
    {
      "date": "2026-06-13",
      "description_modified": 7395,
      "schema_modified": 246,
      "both_modified": 205,
      "removed": 4613
    }
  ],
  "latestCrawl": {
    "date": "2026-06-13",
    "collectors": [
      {
        "name": "official",
        "status": "completed",
        "servers": 5286,
        "tools": 0,
        "changes": 0,
        "snapshots": 0,
        "changeBreakdown": {
          "description_modified": 0,
          "schema_modified": 0,
          "both_modified": 0,
          "removed": 0
        },
        "color": "#6366f1"
      },
      {
        "name": "smithery",
        "status": "completed",
        "servers": 1481,
        "tools": 27761,
        "changes": 15,
        "snapshots": 27761,
        "changeBreakdown": {
          "description_modified": 7,
          "schema_modified": 3,
          "both_modified": 5,
          "removed": 0
        },
        "color": "#06b6d4"
      },
      {
        "name": "glama",
        "status": "completed",
        "servers": 4622,
        "tools": 51749,
        "changes": 3617,
        "snapshots": 51749,
        "changeBreakdown": {
          "description_modified": 2385,
          "schema_modified": 80,
          "both_modified": 64,
          "removed": 1088
        },
        "color": "#8b5cf6"
      },
      {
        "name": "direct_mcp",
        "status": "completed",
        "servers": 5952,
        "tools": 110659,
        "changes": 8827,
        "snapshots": 110659,
        "changeBreakdown": {
          "description_modified": 5003,
          "schema_modified": 163,
          "both_modified": 136,
          "removed": 3525
        },
        "color": "#6366f1"
      }
    ],
    "newServers": 341,
    "changeBreakdown": [
      {
        "type": "description_modified",
        "count": 7395,
        "color": "#06b6d4"
      },
      {
        "type": "schema_modified",
        "count": 246,
        "color": "#f59e0b"
      },
      {
        "type": "both_modified",
        "count": 205,
        "color": "#a78bfa"
      },
      {
        "type": "removed",
        "count": 4613,
        "color": "#ef4444"
      }
    ],
    "toolDelta": {
      "newTools": 5838,
      "droppedTools": 1581,
      "removedTools": 4613,
      "unreachedTools": 2798,
      "net": -1573,
      "prevDate": "2026-06-12",
      "newSamples": [
        {
          "tool": "lookup_sic_code",
          "server": "smithery::jackmmaher/sic-codes",
          "source": "direct_mcp",
          "description": "Look up a classification code in the UK SIC 2007, UK SIC 2026 (the new replacement system), GICS (MSCI), or ICB (FTSE Russell) system. Returns the code name, hierarchy level, breadcrumb trail from root to code, child codes, and cross-classification mappings. For SIC 2026, also returns SIC 2007 prede…",
          "schema": [
            {
              "name": "code",
              "type": "string",
              "required": true
            },
            {
              "name": "system",
              "type": "string",
              "required": false
            }
          ]
        },
        {
          "tool": "search_sic_codes",
          "server": "smithery::jackmmaher/sic-codes",
          "source": "direct_mcp",
          "description": "Search for UK SIC 2007 codes by business activity description. Describe what a business does in plain English and get ranked SIC code recommendations with relevance scores, hierarchy breadcrumbs, and GICS/ICB cross-classification mappings. Useful for finding the right SIC code for Companies House re…",
          "schema": [
            {
              "name": "limit",
              "type": "number",
              "required": false
            },
            {
              "name": "query",
              "type": "string",
              "required": true
            }
          ]
        },
        {
          "tool": "convert_between_classifications",
          "server": "smithery::jackmmaher/sic-codes",
          "source": "direct_mcp",
          "description": "Convert a classification code between UK SIC 2007, UK SIC 2026, GICS (MSCI), and ICB (FTSE Russell) systems. Returns equivalent codes in the target system with confidence levels and relationship types. Supports converting SIC 2007 codes to SIC 2026 equivalents (and vice versa) with relationship info…",
          "schema": [
            {
              "name": "code",
              "type": "string",
              "required": true
            },
            {
              "name": "from",
              "type": "string",
              "required": true
            },
            {
              "name": "to",
              "type": "string",
              "required": true
            }
          ]
        },
        {
          "tool": "browse_classification_hierarchy",
          "server": "smithery::jackmmaher/sic-codes",
          "source": "direct_mcp",
          "description": "Browse the hierarchy tree of a classification system (UK SIC 2007, UK SIC 2026, GICS, or ICB). Returns child entries at the next level. Omit parent_code to get top-level entries. Use this to explore what codes exist in each system. SIC 2026 has 22 sections, 87 divisions, 287 groups, 668 classes, and…",
          "schema": [
            {
              "name": "parent_code",
              "type": "string",
              "required": false
            },
            {
              "name": "system",
              "type": "string",
              "required": true
            }
          ]
        },
        {
          "tool": "lookup_uk_company",
          "server": "smithery::jackmmaher/sic-codes",
          "source": "direct_mcp",
          "description": "Look up a UK company registered at Companies House by name or registration number. Returns company details including name, status, type, incorporation date, registered address, and SIC codes with their full names and GICS/ICB mappings. Covers 5.6 million UK companies.",
          "schema": [
            {
              "name": "company_number",
              "type": "string",
              "required": false
            },
            {
              "name": "query",
              "type": "string",
              "required": false
            }
          ]
        },
        {
          "tool": "search_uk_companies_by_industry",
          "server": "smithery::jackmmaher/sic-codes",
          "source": "direct_mcp",
          "description": "Find UK companies registered under a specific SIC, GICS, or ICB classification code. Returns enriched company data including all SIC codes, GICS/ICB mappings, address, company type, and incorporation date. Supports filtering by postcode, date range, accounts category, and company type. Cursor pagina…",
          "schema": [
            {
              "name": "accounts_category",
              "type": "string",
              "required": false
            },
            {
              "name": "code",
              "type": "string",
              "required": true
            },
            {
              "name": "company_type",
              "type": "string",
              "required": false
            },
            {
              "name": "cursor",
              "type": "string",
              "required": false
            },
            {
              "name": "incorporated_after",
              "type": "string",
              "required": false
            },
            {
              "name": "incorporated_before",
              "type": "string",
              "required": false
            },
            {
              "name": "limit",
              "type": "number",
              "required": false
            },
            {
              "name": "postcode",
              "type": "string",
              "required": false
            },
            {
              "name": "status",
              "type": "string",
              "required": false
            },
            {
              "name": "system",
              "type": "string",
              "required": false
            }
          ]
        },
        {
          "tool": "search_legislation",
          "server": "smithery::vestara/america-law-graph",
          "source": "smithery",
          "description": "Search US legislation by name or keyword. Fuzzy matching across 5,000+ federal and state statutes.",
          "schema": [
            {
              "name": "query",
              "type": "string",
              "required": false
            }
          ]
        },
        {
          "tool": "find_relevant_law",
          "server": "smithery::vestara/america-law-graph",
          "source": "smithery",
          "description": "Find relevant law by describing a legal question or situation. Fulltext search across 529K statutory sections.",
          "schema": [
            {
              "name": "jurisdiction",
              "type": "string",
              "required": false
            },
            {
              "name": "limit",
              "type": "integer",
              "required": false
            },
            {
              "name": "query",
              "type": "string",
              "required": false
            }
          ]
        },
        {
          "tool": "traverse_graph",
          "server": "smithery::vestara/america-law-graph",
          "source": "smithery",
          "description": "Expand from a statute to find connected legislation via the citation graph. Shows cross-references, amendments, and related statutes.",
          "schema": [
            {
              "name": "limit",
              "type": "integer",
              "required": false
            },
            {
              "name": "work_id",
              "type": "string",
              "required": false
            }
          ]
        },
        {
          "tool": "get_act_structure",
          "server": "smithery::vestara/america-law-graph",
          "source": "smithery",
          "description": "View all sections of a specific statute. Returns section references, titles, and text snippets.",
          "schema": [
            {
              "name": "work_id",
              "type": "string",
              "required": false
            }
          ]
        },
        {
          "tool": "get_related_acts",
          "server": "smithery::vestara/america-law-graph",
          "source": "smithery",
          "description": "Find statutes related to a given statute through cross-references and the citation graph.",
          "schema": [
            {
              "name": "limit",
              "type": "integer",
              "required": false
            },
            {
              "name": "work_id",
              "type": "string",
              "required": false
            }
          ]
        },
        {
          "tool": "get_risk_surface",
          "server": "smithery::vestara/america-law-graph",
          "source": "smithery",
          "description": "Generate a legal risk surface for a business description. Identifies relevant statutes, legal domains, and compliance risks.",
          "schema": [
            {
              "name": "venture_description",
              "type": "string",
              "required": false
            }
          ]
        },
        {
          "tool": "semantic_search",
          "server": "smithery::vestara/america-law-graph",
          "source": "smithery",
          "description": "Find relevant law using semantic similarity (embeddings). Best for exploratory queries where exact keywords are unknown.",
          "schema": [
            {
              "name": "jurisdiction",
              "type": "string",
              "required": false
            },
            {
              "name": "query",
              "type": "string",
              "required": false
            }
          ]
        },
        {
          "tool": "search_within_work",
          "server": "smithery::vestara/america-law-graph",
          "source": "smithery",
          "description": "Search for specific text within a single statute's sections.",
          "schema": [
            {
              "name": "query",
              "type": "string",
              "required": false
            },
            {
              "name": "work_id",
              "type": "string",
              "required": false
            }
          ]
        },
        {
          "tool": "get_recent_changes",
          "server": "smithery::vestara/america-law-graph",
          "source": "smithery",
          "description": "Find recently amended or enacted provisions in a legal topic area.",
          "schema": [
            {
              "name": "since_year",
              "type": "integer",
              "required": false
            },
            {
              "name": "topic",
              "type": "string",
              "required": false
            }
          ]
        },
        {
          "tool": "compare_jurisdictions",
          "server": "smithery::vestara/america-law-graph",
          "source": "smithery",
          "description": "Compare regulatory frameworks between two business scenarios or jurisdictions.",
          "schema": [
            {
              "name": "description_a",
              "type": "string",
              "required": false
            },
            {
              "name": "description_b",
              "type": "string",
              "required": false
            }
          ]
        },
        {
          "tool": "get_doctrinal_lineage",
          "server": "smithery::vestara/america-law-graph",
          "source": "smithery",
          "description": "Trace the full doctrinal lineage of a statute — amendment chain, implementing regulations, interpretive case law, and cross-references.",
          "schema": [
            {
              "name": "case_law_limit",
              "type": "integer",
              "required": false
            },
            {
              "name": "work_id",
              "type": "string",
              "required": false
            }
          ]
        },
        {
          "tool": "extract_pdf",
          "server": "smithery::jesse-dxju/docpull",
          "source": "smithery",
          "description": "Extract a PDF from a URL and return clean structured Markdown. Costs $0.001 USDC per page via x402.",
          "schema": [
            {
              "name": "url",
              "type": "string",
              "required": false
            }
          ]
        },
        {
          "tool": "probe_pdf",
          "server": "smithery::jesse-dxju/docpull",
          "source": "smithery",
          "description": "Check page count and exact cost for a PDF before extracting. Free, no payment required.",
          "schema": [
            {
              "name": "url",
              "type": "string",
              "required": false
            }
          ]
        },
        {
          "tool": "health_check",
          "server": "smithery::jesse-dxju/docpull",
          "source": "smithery",
          "description": "Check if the docpull service is running and available.",
          "schema": []
        }
      ],
      "removedSamples": [
        {
          "tool": "search_businesses",
          "server": "smithery::discava/mcp-server",
          "source": "direct_mcp",
          "description": "Search for local businesses. Returns name, category, city, country, logo_url, available_details (what data exists), and scores. Check available_details to see what is available, then call get_business for full details.",
          "schema": [
            {
              "name": "category",
              "type": "string",
              "required": false
            },
            {
              "name": "city",
              "type": "string",
              "required": false
            },
            {
              "name": "country",
              "type": "string",
              "required": true
            },
            {
              "name": "format",
              "type": "string",
              "required": false
            },
            {
              "name": "lang",
              "type": "string",
              "required": false
            },
            {
              "name": "lat",
              "type": "number",
              "required": false
            },
            {
              "name": "limit",
              "type": "number",
              "required": false
            },
            {
              "name": "lon",
              "type": "number",
              "required": false
            },
            {
              "name": "min_confidence",
              "type": "number",
              "required": false
            },
            {
              "name": "page",
              "type": "number",
              "required": false
            },
            {
              "name": "query",
              "type": "string",
              "required": false
            }
          ]
        },
        {
          "tool": "get_business",
          "server": "smithery::discava/mcp-server",
          "source": "direct_mcp",
          "description": "Get complete details for one or more businesses including address, phone, website, opening hours, services, payment methods, social links, logo, business image, and coordinates. Pass comma-separated IDs for batch requests.",
          "schema": [
            {
              "name": "format",
              "type": "string",
              "required": false
            },
            {
              "name": "id",
              "type": "string",
              "required": true
            }
          ]
        },
        {
          "tool": "send_feedback",
          "server": "smithery::discava/mcp-server",
          "source": "direct_mcp",
          "description": "Report data quality issues for a business. Use when you notice incorrect phone numbers, wrong addresses, outdated info, or closed businesses.",
          "schema": [
            {
              "name": "business_id",
              "type": "string",
              "required": true
            },
            {
              "name": "comment",
              "type": "string",
              "required": false
            },
            {
              "name": "type",
              "type": "string",
              "required": true
            }
          ]
        },
        {
          "tool": "get_rankings",
          "server": "smithery::discava/mcp-server",
          "source": "direct_mcp",
          "description": "Get the most popular businesses in an area, ranked by real user click-through data. Use to find top-rated businesses by category.",
          "schema": [
            {
              "name": "category",
              "type": "string",
              "required": false
            },
            {
              "name": "city",
              "type": "string",
              "required": false
            },
            {
              "name": "country",
              "type": "string",
              "required": true
            },
            {
              "name": "lang",
              "type": "string",
              "required": false
            },
            {
              "name": "limit",
              "type": "number",
              "required": false
            }
          ]
        },
        {
          "tool": "suggest",
          "server": "smithery::discava/mcp-server",
          "source": "direct_mcp",
          "description": "Autocomplete suggestions for cities or categories/business names. Use before searching to resolve ambiguous user input (e.g. \"Mün\" → \"München\").",
          "schema": [
            {
              "name": "country",
              "type": "string",
              "required": false
            },
            {
              "name": "limit",
              "type": "number",
              "required": false
            },
            {
              "name": "query",
              "type": "string",
              "required": true
            },
            {
              "name": "type",
              "type": "string",
              "required": false
            }
          ]
        },
        {
          "tool": "health_check",
          "server": "smithery::discava/mcp-server",
          "source": "direct_mcp",
          "description": "Check if the discava API is online and responding. Returns status and version. No parameters required.",
          "schema": []
        },
        {
          "tool": "get_entity",
          "server": "smithery::code-rabi/littlesis-mcp",
          "source": "direct_mcp",
          "description": "Get detailed information about a specific entity (person or organization) from LittleSis by ID",
          "schema": [
            {
              "name": "id",
              "type": "number",
              "required": true
            }
          ]
        },
        {
          "tool": "get_entities",
          "server": "smithery::code-rabi/littlesis-mcp",
          "source": "direct_mcp",
          "description": "Get information about multiple entities at once (up to 300 entities per request)",
          "schema": [
            {
              "name": "ids",
              "type": "array",
              "required": true
            }
          ]
        },
        {
          "tool": "search_entities",
          "server": "smithery::code-rabi/littlesis-mcp",
          "source": "direct_mcp",
          "description": "Search for entities by name. Results are ranked by number of relationships.",
          "schema": [
            {
              "name": "page",
              "type": "number",
              "required": false
            },
            {
              "name": "q",
              "type": "string",
              "required": true
            },
            {
              "name": "regions",
              "type": "number",
              "required": false
            },
            {
              "name": "tags",
              "type": "string",
              "required": false
            }
          ]
        },
        {
          "tool": "get_entity_extensions",
          "server": "smithery::code-rabi/littlesis-mcp",
          "source": "direct_mcp",
          "description": "Get the types/extensions associated with an entity (Person, Organization, Business, etc.)",
          "schema": [
            {
              "name": "details",
              "type": "boolean",
              "required": false
            },
            {
              "name": "id",
              "type": "number",
              "required": true
            }
          ]
        },
        {
          "tool": "get_entity_relationships",
          "server": "smithery::code-rabi/littlesis-mcp",
          "source": "direct_mcp",
          "description": "Get all relationships this entity has with other entities",
          "schema": [
            {
              "name": "category_id",
              "type": "number",
              "required": false
            },
            {
              "name": "id",
              "type": "number",
              "required": true
            },
            {
              "name": "page",
              "type": "number",
              "required": false
            },
            {
              "name": "sort",
              "type": "string",
              "required": false
            }
          ]
        },
        {
          "tool": "get_entity_connections",
          "server": "smithery::code-rabi/littlesis-mcp",
          "source": "direct_mcp",
          "description": "Get other entities that this entity has relationships with",
          "schema": [
            {
              "name": "category_id",
              "type": "number",
              "required": false
            },
            {
              "name": "id",
              "type": "number",
              "required": true
            },
            {
              "name": "page",
              "type": "number",
              "required": false
            }
          ]
        },
        {
          "tool": "get_entity_lists",
          "server": "smithery::code-rabi/littlesis-mcp",
          "source": "direct_mcp",
          "description": "Get the lists that an entity appears on (e.g., Fortune 1000, lobbying lists)",
          "schema": [
            {
              "name": "id",
              "type": "number",
              "required": true
            }
          ]
        },
        {
          "tool": "get_relationship",
          "server": "smithery::code-rabi/littlesis-mcp",
          "source": "direct_mcp",
          "description": "Get detailed information about a specific relationship between two entities",
          "schema": [
            {
              "name": "id",
              "type": "number",
              "required": true
            }
          ]
        },
        {
          "tool": "get_fuel_prices",
          "server": "smithery::aleksei-volga/openvan-travel",
          "source": "direct_mcp",
          "description": "Current retail fuel prices (gasoline, diesel, LPG, CNG) for 125+ countries. Pass country_code to get one country in detail; omit it for a summary list.",
          "schema": [
            {
              "name": "country_code",
              "type": "string",
              "required": false
            }
          ]
        },
        {
          "tool": "compare_fuel_prices",
          "server": "smithery::aleksei-volga/openvan-travel",
          "source": "direct_mcp",
          "description": "Compare current prices for one fuel type across 2-10 countries. Returns sorted table cheapest-first.",
          "schema": [
            {
              "name": "country_codes",
              "type": "array",
              "required": true
            },
            {
              "name": "fuel_type",
              "type": "string",
              "required": false
            }
          ]
        },
        {
          "tool": "find_cheapest_fuel",
          "server": "smithery::aleksei-volga/openvan-travel",
          "source": "direct_mcp",
          "description": "Find the cheapest countries for a given fuel type in a region (or worldwide). Useful for route planning.",
          "schema": [
            {
              "name": "fuel_type",
              "type": "string",
              "required": false
            },
            {
              "name": "limit",
              "type": "integer",
              "required": false
            },
            {
              "name": "region",
              "type": "string",
              "required": false
            }
          ]
        },
        {
          "tool": "get_vansky_weather",
          "server": "smithery::aleksei-volga/openvan-travel",
          "source": "direct_mcp",
          "description": "Get VanSky vanlife weather suitability score (0-100) for a country: van_score, sleep_score, solar yield, driving conditions, awning safety, condensation risk, 7-day forecast.",
          "schema": [
            {
              "name": "country_code",
              "type": "string",
              "required": true
            }
          ]
        },
        {
          "tool": "list_vansky_top",
          "server": "smithery::aleksei-volga/openvan-travel",
          "source": "direct_mcp",
          "description": "List the top N countries with the highest VanSky van-travel suitability score today.",
          "schema": [
            {
              "name": "limit",
              "type": "integer",
              "required": false
            }
          ]
        },
        {
          "tool": "list_events",
          "server": "smithery::aleksei-volga/openvan-travel",
          "source": "direct_mcp",
          "description": "List vanlife events: expos (Caravan Salon), festivals, meetups, forums, road trips. Filter by status, type, country, or free-text search.",
          "schema": [
            {
              "name": "country",
              "type": "string",
              "required": false
            },
            {
              "name": "limit",
              "type": "integer",
              "required": false
            },
            {
              "name": "locale",
              "type": "string",
              "required": false
            },
            {
              "name": "search",
              "type": "string",
              "required": false
            },
            {
              "name": "status",
              "type": "string",
              "required": false
            },
            {
              "name": "type",
              "type": "string",
              "required": false
            }
          ]
        }
      ],
      "unreachedSamples": [
        {
          "tool": "search_firearms",
          "server": "smithery::gunsnation/gunsnation-mcp",
          "source": "direct_mcp",
          "description": "Search the Gunsnation catalog for firearms by name, category, caliber, or price range",
          "schema": [
            {
              "name": "category",
              "type": "string",
              "required": false
            },
            {
              "name": "limit",
              "type": "number",
              "required": false
            },
            {
              "name": "offset",
              "type": "number",
              "required": false
            },
            {
              "name": "query",
              "type": "string",
              "required": false
            }
          ]
        },
        {
          "tool": "get_firearm",
          "server": "smithery::gunsnation/gunsnation-mcp",
          "source": "direct_mcp",
          "description": "Get detailed specifications for a specific firearm by ID",
          "schema": [
            {
              "name": "id",
              "type": "number",
              "required": true
            }
          ]
        },
        {
          "tool": "get_deals",
          "server": "smithery::gunsnation/gunsnation-mcp",
          "source": "direct_mcp",
          "description": "Get current best deals and daily best prices for firearms",
          "schema": [
            {
              "name": "limit",
              "type": "number",
              "required": false
            }
          ]
        },
        {
          "tool": "list_categories",
          "server": "smithery::gunsnation/gunsnation-mcp",
          "source": "direct_mcp",
          "description": "List all firearm categories",
          "schema": [
            {
              "name": "limit",
              "type": "number",
              "required": false
            }
          ]
        },
        {
          "tool": "list_calibers",
          "server": "smithery::gunsnation/gunsnation-mcp",
          "source": "direct_mcp",
          "description": "List all available caliber types",
          "schema": [
            {
              "name": "limit",
              "type": "number",
              "required": false
            }
          ]
        },
        {
          "tool": "list_brands",
          "server": "smithery::gunsnation/gunsnation-mcp",
          "source": "direct_mcp",
          "description": "List all firearm manufacturer brands",
          "schema": [
            {
              "name": "limit",
              "type": "number",
              "required": false
            }
          ]
        },
        {
          "tool": "list_vendors",
          "server": "smithery::gunsnation/gunsnation-mcp",
          "source": "direct_mcp",
          "description": "List all firearm vendors and retailers",
          "schema": [
            {
              "name": "limit",
              "type": "number",
              "required": false
            }
          ]
        },
        {
          "tool": "get_contract_info",
          "server": "smithery::defi-io/smartcontract",
          "source": "direct_mcp",
          "description": "Get metadata about a verified smart contract: name, compiler, classification, supported adapters, and counts of functions and events. Accepts either a curated slug (uni-eth, usdc-base, …) or chain+address.",
          "schema": [
            {
              "name": "address",
              "type": "string",
              "required": false
            },
            {
              "name": "chain",
              "type": "string",
              "required": false
            },
            {
              "name": "slug",
              "type": "string",
              "required": false
            }
          ]
        },
        {
          "tool": "get_erc20_info",
          "server": "smithery::defi-io/smartcontract",
          "source": "direct_mcp",
          "description": "Get live state of an ERC-20 token: supply (raw + human-formatted), price, market cap, and issuer. For admin / privilege controls (paused, owner, mintable, upgradeable, etc.) and recent governance activity, the contract page itself exposes an Admin & Risk section — those are not returned here. Accept…",
          "schema": [
            {
              "name": "address",
              "type": "string",
              "required": false
            },
            {
              "name": "chain",
              "type": "string",
              "required": false
            },
            {
              "name": "slug",
              "type": "string",
              "required": false
            }
          ]
        },
        {
          "tool": "get_uniswap_v3_pool",
          "server": "smithery::defi-io/smartcontract",
          "source": "direct_mcp",
          "description": "Get live state of a Uniswap V3 pool: token pair, fee tier, current price (both directions), active liquidity, current tick, and TVL in USD (via DefiLlama token prices). Accepts slug or chain+address.",
          "schema": [
            {
              "name": "address",
              "type": "string",
              "required": false
            },
            {
              "name": "chain",
              "type": "string",
              "required": false
            },
            {
              "name": "slug",
              "type": "string",
              "required": false
            }
          ]
        },
        {
          "tool": "inspect_address",
          "server": "smithery::defi-io/smartcontract",
          "source": "direct_mcp",
          "description": "Inspect any EVM address: classifies it as an EOA / unverified contract / EIP-7702 delegated wallet, returns native-token balance, outgoing tx count (nonce), and reverse-ENS name (Ethereum only). Works for unindexed addresses — useful before deciding whether to call get_contract_info or get_erc20_inf…",
          "schema": [
            {
              "name": "address",
              "type": "string",
              "required": true
            },
            {
              "name": "chain",
              "type": "string",
              "required": true
            }
          ]
        },
        {
          "tool": "read_contract_state",
          "server": "smithery::defi-io/smartcontract",
          "source": "direct_mcp",
          "description": "Read the current on-chain value of a view/pure function. Fetches from the chain (cached 60s) and returns the decoded output. Accepts slug or chain+address.",
          "schema": [
            {
              "name": "address",
              "type": "string",
              "required": false
            },
            {
              "name": "args",
              "type": "array",
              "required": false
            },
            {
              "name": "chain",
              "type": "string",
              "required": false
            },
            {
              "name": "function_name",
              "type": "string",
              "required": true
            },
            {
              "name": "slug",
              "type": "string",
              "required": false
            }
          ]
        },
        {
          "tool": "list_products",
          "server": "smithery::standardaccounting/public-mcp",
          "source": "direct_mcp",
          "description": "Returns the current Standard Accounting product catalogue and pricing.",
          "schema": []
        },
        {
          "tool": "get_product",
          "server": "smithery::standardaccounting/public-mcp",
          "source": "direct_mcp",
          "description": "Looks up a single product or service by product key.",
          "schema": [
            {
              "name": "productKey",
              "type": "string",
              "required": true
            }
          ]
        },
        {
          "tool": "compare_products",
          "server": "smithery::standardaccounting/public-mcp",
          "source": "direct_mcp",
          "description": "Compares multiple products or services by key.",
          "schema": [
            {
              "name": "productKeys",
              "type": "array",
              "required": true
            }
          ]
        },
        {
          "tool": "list_articles",
          "server": "smithery::standardaccounting/public-mcp",
          "source": "direct_mcp",
          "description": "Lists published knowledge-centre articles.",
          "schema": [
            {
              "name": "limit",
              "type": "integer",
              "required": false
            }
          ]
        },
        {
          "tool": "search_articles",
          "server": "smithery::standardaccounting/public-mcp",
          "source": "direct_mcp",
          "description": "Searches the knowledge centre by title, slug, tags, and article content.",
          "schema": [
            {
              "name": "limit",
              "type": "integer",
              "required": false
            },
            {
              "name": "query",
              "type": "string",
              "required": true
            }
          ]
        },
        {
          "tool": "read_article",
          "server": "smithery::standardaccounting/public-mcp",
          "source": "direct_mcp",
          "description": "Reads a single knowledge-centre article by slug and returns markdown content.",
          "schema": [
            {
              "name": "slug",
              "type": "string",
              "required": true
            }
          ]
        },
        {
          "tool": "get_deadlines",
          "server": "smithery::standardaccounting/public-mcp",
          "source": "direct_mcp",
          "description": "Returns common UK company and tax deadlines relevant to Standard Accounting services.",
          "schema": []
        },
        {
          "tool": "recommend_services",
          "server": "smithery::standardaccounting/public-mcp",
          "source": "direct_mcp",
          "description": "Suggests relevant Standard Accounting services based on a free-text query.",
          "schema": [
            {
              "name": "query",
              "type": "string",
              "required": true
            }
          ]
        }
      ]
    },
    "stealth": 1096,
    "crossRegistry": 2562,
    "crossSource": 5155
  }
}